medil/__init__.py
medil/ecc_algorithms.py
medil/evaluate.py
medil/examples.py
medil/graph.py
medil/independence_testing.py
medil/models.py
medil/sample.py
medil/vae.py
medil/visualize.py
medil-1.1.0.dist-info/LICENSE.md
medil-1.1.0.dist-info/METADATA
medil-1.1.0.dist-info/WHEEL
medil-1.1.0.dist-info/top_level.txt
medil-1.1.0.dist-info/RECORD
