Metadata-Version: 2.1
Name: medil
Version: 1.1.0
Summary: MeDIL is a Python package for causal factor analysis with the (me)asurement (d)ependence (i)nducing (l)atent causal model framework.
Author: Alex Markham
Author-email: alex.markham@causal.dev
License: GNU Affero General Public License version 3 or later (AGPLv3+)
License-File: LICENSE.md
Requires-Dist: dcor
Requires-Dist: matplotlib
Requires-Dist: networkx
Requires-Dist: seaborn
Requires-Dist: scikit-learn
Requires-Dist: torch
